{
    "media": [
        {
            "question": [
                "What is the name of the monkey who played Dexter in Night at the Museum?"
            ],
            "correctAnswer": [
                "Crystal"
            ],
            "wrongAnswer": [
                "Peggy",
                "Bonzo",
                "Belle"
            ]
        },
        {
            "question": [
                "What is the name of Patty and Selma’s lizard from The Simpsons?"
            ],
            "correctAnswer": [
                "Jub-Jub"
            ],
            "wrongAnswer": [
                "Chirpy Boy",
                "Mojo",
                "Raymond"
            ]
        },
        {
            "question": [
                "Which of these events have NOT been featured in the Olympic Games?"
            ],
            "correctAnswer": [
                "Tejo"
            ],
            "wrongAnswer": [
                "Steeplechase",
                "Basque Pelota",
                "Korfball"
            ]
        },
        {
            "question": [
                "By how many pixels is the Minecraft toolbar off centre by in bedrock edition?"
            ],
            "correctAnswer": [
                "A single pixel"
            ],
            "wrongAnswer": [
                "2 pixels",
                "Over 10 pixels",
                "Trick question, it’s on center"
            ]
        },
        {
            "question": [
                "What Pokemon is number 392 in the national dex?"
            ],
            "correctAnswer": [
                "Infernape"
            ],
            "wrongAnswer": [
                "Lilligant",
                "Latias",
                "Pachirisu"
            ]
        },
        {
            "question": [
                "What’s the code name of the game Riot Games revealed in October 2019?"
            ],
            "correctAnswer": [
                "Project F, a possible RPG"
            ],
            "wrongAnswer": [
                "Project A, a possible FPS",
                "Project B, a possible card game",
                "Project L, a possible fighting game"
            ]
        },
        {
            "question": [
                "What level is the Ukiki enemy found in Super Mario 64?"
            ],
            "correctAnswer": [
                "Tall, Tall Mountain"
            ],
            "wrongAnswer": [
                "Hazy Maze Cave",
                "Tick Tock Clock",
                "Big Boo’s Haunt"
            ]
        },
        {
            "question": [
                "What is the most watched anime in the UK as of 2023?"
            ],
            "correctAnswer": [
                "Attack on Titan"
            ],
            "wrongAnswer": [
                "Death Note",
                "Demon Slayer: Kimetsu No Yaiba",
                "Fullmetal Alchemist: Brotherhood"
            ]
        },
        {
            "question": [
                "Which of these is not an actual character in the Five Nights at Freddy’s franchise?"
            ],
            "correctAnswer": [
                "Puppet Freddy"
            ],
            "wrongAnswer": [
                "Virtua Freddy",
                "Great Escape Golden Freddy",
                "Baron Von Bear"
            ]
        },
        {
            "question": [
                "What is the name of the main Caucasian character in the movie Black Panther?"
            ],
            "correctAnswer": [
                "Everett K. Ross"
            ],
            "wrongAnswer": [
                "Dane Whitman",
                "Franklin Richards",
                "Nathan Garrett"
            ]
        }
    ],
    "science": [
        {
            "question": [
                "What is the diameter of the planet Pluto in inches?"
            ],
            "correctAnswer": [
                "93.56 million"
            ],
            "wrongAnswer": [
                "2.1 billion",
                "44.32 million",
                "9.1 billion"
            ]
        },
        {
            "question": [
                "How many species of fly are there in the UK?"
            ],
            "correctAnswer": [
                "Around 7,000"
            ],
            "wrongAnswer": [
                "Around 1,000",
                "Around 150,000",
                "Around 4,500"
            ]
        },
        {
            "question": [
                "How much does the internet roughly weigh?"
            ],
            "correctAnswer": [
                "As much as a tennis ball"
            ],
            "wrongAnswer": [
                "As much as a bowling ball",
                "As much as a basket ball",
                "As much as a ping pong ball"
            ]
        },
        {
            "question": [
                "Where do grasshoppers have ears?"
            ],
            "correctAnswer": [
                "Their stomach"
            ],
            "wrongAnswer": [
                "Their legs",
                "Their antenna",
                "Their back"
            ]
        },
        {
            "question": [
                "Which of these nuts aren’t actually a nut?"
            ],
            "correctAnswer": [
                "Peanuts"
            ],
            "wrongAnswer": [
                "Hazelnuts",
                "Cashews",
                "Pistachios"
            ]
        },
        {
            "question": [
                "What’s the name for hibernating through the summer?"
            ],
            "correctAnswer": [
                "Aestivation"
            ],
            "wrongAnswer": [
                "Hybernation",
                "Brumation",
                "Diapause"
            ]
        },
        {
            "question": [
                "Which of these is not a real scientific name?"
            ],
            "correctAnswer": [
                "Horse Horse Horse"
            ],
            "wrongAnswer": [
                "Gorilla Gorilla Gorilla",
                "Giraffa Giraffa Giraffa",
                "Lynx Lynx Lynx"
            ]
        },
        {
            "question": [
                "Which of these reptiles is more closely related to birds than lizards?"
            ],
            "correctAnswer": [
                "Crocodile"
            ],
            "wrongAnswer": [
                "Chameleon",
                "Iguana",
                "Komodo dragon"
            ]
        },
        {
            "question": [
                "How long will it take for Asia and America to collide into one continent?"
            ],
            "correctAnswer": [
                "200 million years"
            ],
            "wrongAnswer": [
                "500 billion years",
                "700 trillion years",
                "1 quadrillion years"
            ]
        },
        {
            "question": [
                "Which of the following cannot be seen from space?"
            ],
            "correctAnswer": [
                "The pyramids of Giza"
            ],
            "wrongAnswer": [
                "The green houses of Almeria",
                "The Corn mazes from Minnesota",
                "The Cooling Pond of Chernobyl"
            ]
        }
    ],
    "history": [
        {
            "question": [
                "Who designed the Indian palace Malik Bagh?"
            ],
            "correctAnswer": [
                "Eckart Muthesius"
            ],
            "wrongAnswer": [
                "Ickbar Bigglestein",
                "Jacob Burckhardt",
                "Datheid Bluterost"
            ]
        },
        {
            "question": [
                "Which one of Stalin’s opponents in the power struggle died from an icepick to the head?"
            ],
            "correctAnswer": [
                "Leon Trotsky"
            ],
            "wrongAnswer": [
                "Lev Kamenev",
                "Grigory Zinoviev",
                "Nikolai Bukharin"
            ]
        },
        {
            "question": [
                "What is the 56th word in the very first Oxford Dictionary?"
            ],
            "correctAnswer": [
                "Arista"
            ],
            "wrongAnswer": [
                "Alpine",
                "Arisen",
                "Aerial"
            ]
        },
        {
            "question": [
                "When were post-it notes invented?"
            ],
            "correctAnswer": [
                "1968"
            ],
            "wrongAnswer": [
                "1980",
                "1946",
                "1953"
            ]
        },
        {
            "question": [
                "When were passports invented?"
            ],
            "correctAnswer": [
                "1414"
            ],
            "wrongAnswer": [
                "1921",
                "1892",
                "1505"
            ]
        },
        {
            "question": [
                "How many highways are there in the world numbered 252?"
            ],
            "correctAnswer": [
                "28"
            ],
            "wrongAnswer": [
                "30",
                "12",
                "25"
            ]
        },
        {
            "question": [
                "What are the three treasures of Taoism?"
            ],
            "correctAnswer": [
                "Compassion, frugality, and humility"
            ],
            "wrongAnswer": [
                "Courage, wisdom, and kindness",
                "Willpower, hope, and love",
                "Self-improvement, respect, and politeness"
            ]
        },
        {
            "question": [
                "What animal did the Polish enlist as a soldier during World War II?"
            ],
            "correctAnswer": [
                "A bear"
            ],
            "wrongAnswer": [
                "A bison",
                "A wolf",
                "A white-tailed eagle"
            ]
        },
        {
            "question": [
                "How long did Queen Jane Grey rule England for?"
            ],
            "correctAnswer": [
                "9 days"
            ],
            "wrongAnswer": [
                "34 days",
                "53 days",
                "1 day"
            ]
        },
        {
            "question": [
                "Which of these substances was never used as medicine?"
            ],
            "correctAnswer": [
                "Mayonnaise"
            ],
            "wrongAnswer": [
                "Ketchup",
                "Chili sauce",
                "Soy sauce"
            ]
        }
    ],
    "rats": [
        {
            "question": [
                "What is the name of the first rat to go to space?"
            ],
            "correctAnswer": [
                "Hector"
            ],
            "wrongAnswer": [
                "Splinter",
                "Victor",
                "Mickey"
            ]
        },
        {
            "question": [
                "On average, how close are you to a rat right this second?"
            ],
            "correctAnswer": [
                "Six feet"
            ],
            "wrongAnswer": [
                "One mile",
                "Nine metres",
                "FIfteen centimetres"
            ]
        },
        {
            "question": [
                "Which of these things can a rat not do?"
            ],
            "correctAnswer": [
                "Gag"
            ],
            "wrongAnswer": [
                "Laugh",
                "Eye boggle",
                "Sneeze"
            ]
        },
        {
            "question": [
                "What is the name of the rat in Horrible Histories?"
            ],
            "correctAnswer": [
                "Rattus Rattus"
            ],
            "wrongAnswer": [
                "Ratthew T. Rat",
                "Ratta Tatta",
                "He doesn’t have a name"
            ]
        },
        {
            "question": [
                "What is the average length of a rat tail?"
            ],
            "correctAnswer": [
                "Six inches"
            ],
            "wrongAnswer": [
                "Nine inches",
                "Three inches",
                "Eight inches"
            ]
        },
        {
            "question": [
                "What is the scientific name for “rat”?"
            ],
            "correctAnswer": [
                "Rattus"
            ],
            "wrongAnswer": [
                "Rattas",
                "Rattata",
                "Rattaelada"
            ]
        },
        {
            "question": [
                "How many bones does a rat have?"
            ],
            "correctAnswer": [
                "223"
            ],
            "wrongAnswer": [
                "206",
                "142",
                "91"
            ]
        },
        {
            "question": [
                "What is “rat” in Chinese?"
            ],
            "correctAnswer": [
                "Shu"
            ],
            "wrongAnswer": [
                "Rat",
                "Tar",
                "Mai"
            ]
        },
        {
            "question": [
                "Which of these years was the Chinese Year of the Rat?"
            ],
            "correctAnswer": [
                "2020"
            ],
            "wrongAnswer": [
                "2018",
                "2017",
                "2024"
            ]
        },
        {
            "question": [
                "“Ratman’s Notebooks” is a short horror novel written by Stephen Gilbert, an author from which country?"
            ],
            "correctAnswer": [
                "United Kingdom"
            ],
            "wrongAnswer": [
                "U.S.A",
                "Greece",
                "Hungary"
            ]
        }
    ],
    "geography": [
        {
            "question": [
                "How many states does Brazil have?"
            ],
            "correctAnswer": [
                "26"
            ],
            "wrongAnswer": [
                "29",
                "35",
                "42"
            ]
        },
        {
            "question": [
                "If the U.S. states were to be listed alphabetically, which would be listed 26th?"
            ],
            "correctAnswer": [
                "Montana"
            ],
            "wrongAnswer": [
                "Missouri",
                "Nebraska",
                "Mississippi"
            ]
        },
        {
            "question": [
                "Ossetians are an ethnic group belonging to which country?"
            ],
            "correctAnswer": [
                "Iran"
            ],
            "wrongAnswer": [
                "Hungary",
                "Russia",
                "Mongolia"
            ]
        },
        {
            "question": [
                "What’s the maximum temperature that the hottest part of the Amazon river can get?"
            ],
            "correctAnswer": [
                "99.1 ℃"
            ],
            "wrongAnswer": [
                "102.9 ℃",
                "198.5 ℃",
                "198.5 °F"
            ]
        },
        {
            "question": [
                "Where is the city where everyone lives under one roof located?"
            ],
            "correctAnswer": [
                "Alaska"
            ],
            "wrongAnswer": [
                "Croatia",
                "Belgium",
                "Monaco"
            ]
        },
        {
            "question": [
                "Which country is not connected to Namibia on the map?"
            ],
            "correctAnswer": [
                "Zimbabwe"
            ],
            "wrongAnswer": [
                "Botswana",
                "South Africa",
                "Angola"
            ]
        },
        {
            "question": [
                "How many time zones does Russia cover?"
            ],
            "correctAnswer": [
                "11"
            ],
            "wrongAnswer": [
                "9",
                "14",
                "7"
            ]
        },
        {
            "question": [
                "What’s the flattest country on the planet?"
            ],
            "correctAnswer": [
                "The Maldives"
            ],
            "wrongAnswer": [
                "Vatican City",
                "Nauru",
                "Tuvalu"
            ]
        },
        {
            "question": [
                "Which of these natural disasters is least likely to happen on the equator?"
            ],
            "correctAnswer": [
                "Tornado"
            ],
            "wrongAnswer": [
                "Drought",
                "Flash flood",
                "Earthquakes"
            ]
        },
        {
            "question": [
                "What’s the longest underground river?"
            ],
            "correctAnswer": [
                "Puerto Princesa in Philippines"
            ],
            "wrongAnswer": [
                "Cenote Angelita in Mexico",
                "Submarine Channel in the Black Sea",
                "Phong Nha River in Vietnam"
            ]
        }
    ],
    "bonus": [
        {
            "question": [
                "Why are my parents arguing?"
            ],
            "correctAnswer": [
                "Don’t worry about it"
            ],
            "wrongAnswer": [
                "It’s your fault",
                "It’s my fault",
                "Political disagreement"
            ]
        },
        {
            "question": [
                "What number am I thinking of?"
            ],
            "wrongAnswer": [
                "23",
                "91",
                "68",
                "3889"
            ],
            "allWrong":  true
        },
        {
            "question": [
                "Do you guys even like me?"
            ],
            "correctAnswer": [
                "Not really…"
            ],
            "wrongAnswer": [
                "Yes!",
                "100% absolutely!",
                "Can I go home now"
            ]
        },
        {
            "question": [
                "What is our artist eating as we write these questions?"
            ],
            "correctAnswer": [
                "Noodles"
            ],
            "wrongAnswer": [
                "Pasta",
                "Cookie",
                "Sandwich"
            ]
        },
        {
            "question": [
                "What is the Tower of Babel?"
            ],
            "correctAnswer": [
                "Wanpela taua ol i wokim bilong go antap long heven"
            ],
            "wrongAnswer": [
                "Sijiui",
                "मला माहित नाही",
                "Ndaikuaái"
            ]
        },
        {
            "question": [
                "How many wheels does an 18-wheeler have?"
            ],
            "correctAnswer": [
                "19"
            ],
            "wrongAnswer": [
                "18",
                "17",
                "4"
            ]
        },
        {
            "question": [
                "Should you start a podcast?"
            ],
            "correctAnswer": [
                "No"
            ],
            "wrongAnswer": [
                "Yes",
                "Unsure",
                "What’s a podcast"
            ]
        },
        {
            "question": [
                "Witch pf teh fullowing werds iz spalt corectly?"
            ],
            "correctAnswer": [
                "Corectly"
            ],
            "wrongAnswer": [
                "Incorrecyly",
                "Supercalifragilisticexpialidocious",
                "Correctly"
            ]
        },
        {
            "question": [
                "Hi"
            ],
            "correctAnswer": [
                "This is not a question"
            ],
            "wrongAnswer": [
                "Hello",
                "B",
                "Hi"
            ]
        },
        {
            "question": [
                "I have a face and yet can not see, hear, talk, or taste. I have 2 hands and yet cannot hold things. I keep track of something that I personally do not know. What am I?"
            ],
            "correctAnswer": [
                "A really &%$# up man."
            ],
            "wrongAnswer": [
                "A River",
                "Nature",
                "A Clock"
            ]
        },
        {
            "question": [
                "Which of these questions is real?"
            ],
            "correctAnswer": [
                "Can a match box?"
            ],
            "wrongAnswer": [
                "If a woodpecker wood pecked wood, would the pecker wood be pecked?",
                "What is MXXXVII+𝋲?",
                "What is the best game ever?"
            ]
        },
        {
            "question": [
                "I need to go for this round. Please don’t do anything."
            ],
            "wrongAnswer": [
                "Eat the cheese",
                "Escape",
                "Run a mini gameshow",
                "Stay and sit still",
            ],
            "allWrong":  true,
            "emptyCorrect": true
        }
    ]
}