{
    "itemList": [
        {
            "name": "Name",
            "code": "code",
            "description": "Stuff About the Item",
            "health": 0,
            "damage": 0,
            "speed": 0,
            "vision": 0,
            "crit": 0
        },
        {
            "name": "Name",
            "code": "code",
            "description": "Stuff About the Item",
            "health": 0,
            "damage": 0,
            "speed": 0,
            "vision": 0,
            "crit": 0
        }
    ]
}